Homework_Assignment_3/serial_adder.v
module tb_serial_adder();
	
	wire [3:0] out;
	reg [3:0] in1, in2;
	reg clk, rst, load;

	serial_adder uut (out, in1, in2, clk, rst, load);

	initial begin
		#00 clk = 1'b0;
		forever #10 clk = ~clk;
	end

	initial begin
		#00 in1 = 4'b0110; in2 = 4'b0111;
		#00 rst = 1'b1; load = 1'b0;
		#5 rst = 1'b0; load = 1'b1;
		#10 rst = 1'b1; load = 1'b0;
		#1000 $finish;
	end

	initial begin
		$dumpfile("serial_adder.vcd");
		$dumpvars;
	end
endmodule

module serial_adder(out, in1, in2, clk, rst, load);

	output [3:0] out;
	input wire [3:0] in1, in2;
	input wire clk, rst, load;

	wire data1, data2;
	wire sum;
	wire cout, cin;
	
	piso p1 (data1, in1, load, clk);
	piso p2 (data2, in2, load, clk);

	full_adder fa (sum, cout, data1, data2, cin);
	dff_neg_async dff (cin, cout, clk, rst);

	sipo s1 (out, sum, clk, rst);
endmodule

module dff_neg_async(q, d, clk, rst);

	output reg q;
	input d,clk,rst;

	always @(posedge clk or negedge rst)
		// Positive Edge Triggered Clock and Active Low Asynchronous reset.
		begin
			if(!rst) q <= 1'b0;
			else 	q <= d;
		end
endmodule

module full_adder(sum, cout, a, b, cin);

	output sum,cout;
	input a,b,cin;

	assign sum = a^b^cin;
	assign cout = (a&b)|(a&cin)|(b&cin);
	//assign {cout,sum}=a+b+cin;
	//The above statements de-concatenates the two bit result of the addition and stores the MSB to cout and LSB to sum
endmodule

module piso (dataout, datain, load, clk);
	
	output reg dataout;
	input wire clk, load;
	input wire [3:0] datain;

	reg [3:0] hold;
	
	always @ (load)
				hold = datain;
	always @ (posedge clk)
	begin
		dataout <= hold[0];
		hold <= {1'b0, hold[3:1]};
	end
endmodule

module sipo (dataout, datain, clk, rst);
	
	output reg [3:0] dataout;
	input wire clk, rst;
	input wire datain;

	reg [3:0] hold;

	always @ (posedge clk or negedge rst)
	begin
		if (!rst)
			hold <= 4'b0000;
		else begin
			hold[0] <= datain;
			hold[1] <= hold[0];
			hold[2] <= hold[1];
			hold[3] <= hold[2];
		end
	end

	always @ (*)
		dataout = hold;
endmodule

Homework_Assignment_3/serial_adder.vcd
$date
	Tue Apr 10 11:29:18 2018
$end
$version
	Icarus Verilog
$end
$timescale
	1s
$end
$scope module tb_serial_adder $end
$var wire 4 ! out [3:0] $end
$var reg 1 " clk $end
$var reg 4 # in1 [3:0] $end
$var reg 4 $ in2 [3:0] $end
$var reg 1 % load $end
$var reg 1 & rst $end
$scope module uut $end
$var wire 1 " clk $end
$var wire 4 ' in1 [3:0] $end
$var wire 4 ( in2 [3:0] $end
$var wire 1 % load $end
$var wire 1 & rst $end
$var wire 1 ) sum $end
$var wire 4 * out [3:0] $end
$var wire 1 + data2 $end
$var wire 1 , data1 $end
$var wire 1 - cout $end
$var wire 1 . cin $end
$scope module dff $end
$var wire 1 " clk $end
$var wire 1 & rst $end
$var wire 1 - d $end
$var reg 1 . q $end
$upscope $end
$scope module fa $end
$var wire 1 . cin $end
$var wire 1 - cout $end
$var wire 1 ) sum $end
$var wire 1 + b $end
$var wire 1 , a $end
$upscope $end
$scope module p1 $end
$var wire 1 " clk $end
$var wire 4 / datain [3:0] $end
$var wire 1 % load $end
$var reg 1 , dataout $end
$var reg 4 0 hold [3:0] $end
$upscope $end
$scope module p2 $end
$var wire 1 " clk $end
$var wire 4 1 datain [3:0] $end
$var wire 1 % load $end
$var reg 1 + dataout $end
$var reg 4 2 hold [3:0] $end
$upscope $end
$scope module s1 $end
$var wire 1 " clk $end
$var wire 1 ) datain $end
$var wire 1 & rst $end
$var reg 4 3 dataout [3:0] $end
$var reg 4 4 hold [3:0] $end
$upscope $end
$upscope $end
$upscope $end
$enddefinitions $end
#0
$dumpvars
bx 4
bx 3
b111 2
b111 1
b110 0
b110 /
x.
x-
x,
x+
bx *
x)
b111 (
b110 '
1&
0%
b111 $
b110 #
0"
bx !
$end
#5
b0 !
b0 *
b0 3
0.
b0 4
1%
0&
#10
0-
1)
b11 0
0,
b11 2
1+
1"
#15
b111 2
b110 0
0%
1&
#20
0"
#30
b1 !
b1 *
b1 3
b1 4
b11 2
b11 0
1"
#40
0"
#50
1-
0)
b11 !
b11 *
b11 3
b11 4
b1 0
1,
b1 2
1"
#60
0"
#70
1)
b110 !
b110 *
b110 3
1.
b110 4
b0 2
b0 0
1"
#80
0"
#90
0-
b1101 !
b1101 *
b1101 3
b1101 4
0,
0+
1"
#100
0"
#110
0)
b1011 !
b1011 *
b1011 3
0.
b1011 4
1"
#120
0"
#130
b110 !
b110 *
b110 3
b110 4
1"
#140
0"
#150
b1100 !
b1100 *
b1100 3
b1100 4
1"
#160
0"
#170
b1000 !
b1000 *
b1000 3
b1000 4
1"
#180
0"
#190
b0 !
b0 *
b0 3
b0 4
1"
