Lab1_Dataflow_Modelling/alu_4bit.v
`timescale 1ns/10ps

`define sub 	= 3'b000
`define add 	= 3'b001 
`define exor 	= 3'b010
`define andab 	= 3'b011
`define orab 	= 3'b100
`define shr 	= 3'b101 // shift right a by 1 bit 
`define shl 	= 3'b110 // shift left a by 1 bit 
`define sar 	= 3'b111 // arithmetic shift right a by 1 bit 

module tb_alu_4bit();

wire [3:0] out;
reg [3:0] a,b;
reg [2:0] op;
alu_4bit uut(out,a,b,op);

initial
begin
#00  op=3'd0; a=4'd7; b=4'd3;
#20  op=3'd1; a=4'd7; b=4'd3;
#20  op=3'd2; a=4'd7; b=4'd3;
#20  op=3'd3; a=4'd7; b=4'd3;
#20  op=3'd4; a=4'd7; b=4'd3;
#20  op=3'd5; a=4'd7; b=4'd3;
#20  op=3'd6; a=4'd7; b=4'd3;
#20  op=3'd7; a=4'd7; b=4'd3;
#20  $stop;
end

initial
begin
$monitor("time=%3d, a=%4d, b=%4d, op=%3d, out=%7d",$time,a,b,op,out);
end
	
initial
begin
$dumpfile("alu_4bit.vcd");
$dumpvars;
end
endmodule
 
module alu_4bit(out,a,b,op);
	
output [3:0] out;
input [3:0] a,b;
input [2:0] op;

wire [3:0] y0,y1,y2,y3,y4,y5,y6,y7; 

assign y0 = a-b ; 
assign y1 = a+b ; 
assign y2 = a^b ; 
assign y3 = a&b ; 
assign y4 = a|b ; 
assign y5 = a >> 1'b1; 
assign y6 = a << 1'b1 ; 
assign y7 = {a[3],a[3:1]} ; 

assign out = op[2]?(op[1]?(op[0]?y7:y6):(op[0]?y5:y4)):(op[1]?(op[0]?y3:y2):(op[0]?y1:y0)); 
//what output is to be printed will be decided on the three bit opcode
endmodule

Lab1_Dataflow_Modelling/alu_4bit.vcd
$date
	Tue Jan 16 15:50:05 2018
$end
$version
	Icarus Verilog
$end
$timescale
	10ps
$end
$scope module tb_alu_4bit $end
$var wire 4 ! out [3:0] $end
$var reg 4 " a [3:0] $end
$var reg 4 # b [3:0] $end
$var reg 3 $ op [2:0] $end
$scope module uut $end
$var wire 4 % a [3:0] $end
$var wire 4 & b [3:0] $end
$var wire 3 ' op [2:0] $end
$var wire 4 ( y2 [3:0] $end
$var wire 4 ) y3 [3:0] $end
$var wire 4 * y4 [3:0] $end
$var wire 4 + y7 [3:0] $end
$var wire 4 , y6 [3:0] $end
$var wire 4 - y5 [3:0] $end
$var wire 4 . y1 [3:0] $end
$var wire 4 / y0 [3:0] $end
$var wire 4 0 out [3:0] $end
$upscope $end
$upscope $end
$enddefinitions $end
#0
$dumpvars
b100 0
b100 /
b1010 .
b11 -
b1110 ,
b11 +
b111 *
b11 )
b100 (
b0 '
b11 &
b111 %
b0 $
b11 #
b111 "
b100 !
$end
#2000
b1010 !
b1010 0
b1 $
b1 '
#4000
b100 !
b100 0
b10 $
b10 '
#6000
b11 !
b11 0
b11 $
b11 '
#8000
b111 !
b111 0
b100 $
b100 '
#10000
b11 !
b11 0
b101 $
b101 '
#12000
b1110 !
b1110 0
b110 $
b110 '
#14000
b11 !
b11 0
b111 $
b111 '
