Lab1_Dataflow_Modelling/half_adder.v
`timescale 1ns/10ps

module tb_half_adder(); 

	reg x,y ; 
	wire s,c ; 

	half_adder uut (.sum(s),.carry(c),.a(x),.b(y));

	initial 
	begin 
		#00 x=1'b0 ; y=1'b0 ; 
		#20 x=1'b0 ; y=1'b1 ; 
		#20 x=1'b1 ; y=1'b0 ; 
		#20 x=1'b1 ; y=1'b1 ; 
		#20 $stop ; 
	end

	initial $monitor("t=%3d, x=%b,y=%b,carry=%b,sum=%b",$time,x,y,c,s); 

	initial
	begin
		$dumpfile("half_adder.vcd");
		$dumpvars;
	end
		
endmodule

module half_adder(sum,carry,a,b);

	output sum,carry ;
	input a,b ;

	assign #15 sum 	= a ^ b ; 
	assign #10 carry = a & b ;
endmodule

Lab1_Dataflow_Modelling/half_adder.vcd
$date
	Tue Jan 16 15:19:21 2018
$end
$version
	Icarus Verilog
$end
$timescale
	10ps
$end
$scope module tb_half_adder $end
$var wire 1 ! s $end
$var wire 1 " c $end
$var reg 1 # x $end
$var reg 1 $ y $end
$scope module uut $end
$var wire 1 # a $end
$var wire 1 $ b $end
$var wire 1 " carry $end
$var wire 1 ! sum $end
$upscope $end
$upscope $end
$enddefinitions $end
#0
$dumpvars
0$
0#
x"
x!
$end
#1000
0"
#1500
0!
#2000
1$
#3500
1!
#4000
0$
1#
#6000
1$
#7000
1"
#7500
0!
