Lab3_Structural_Modelling/binary_counter.v
//Synchronous Binary up-counter using structural modeling Style
//use of Negative Edge Triggered D flip flop with active high asynchronous reset
// Primitive Gates

`timescale 1ns/1ps

module tb_binary_counter();

reg rst,clock;
wire [3:0] out;

binary_counter uut(out,rst,clock);


always #10 clock = ~clock;
	
initial
	begin
	clock = 0; rst=0;
	#20 rst = 1;
	#40 rst = 0;
	#100 rst = 1;
	#40 rst = 0;
	#800 $stop;
	end
		
endmodule


module binary_counter (count, rst, clk);

input clk,rst;
output [3:0] count;

wire [3:0]cnt_b ; // has the negation of the count signals 
wire d2,d3,d4 ; // inputs to fliflops numbered 2,3,4 respectively 
wire w1,w2,w3,w4,w5 ; 

not I1 (cnt_b[0],count[0]);
not I2 (cnt_b[1],count[1]);
not I3 (cnt_b[2],count[2]);
not I4 (cnt_b[3],count[3]);

xor X1 (w5,count[0],count[1]); 
and A6 (d2,w5,cnt_b[3]); 

and A1 (w1,count[0],count[1]);
xor X2 (w2,count[2],w1);
and A2 (d3,cnt_b[3],w2);

and A3 (w3,count[3],cnt_b[2],cnt_b[1],cnt_b[0]);
and A4 (w4,cnt_b[3],count[2],count[1],count[0]);
or O1  (d4,w3,w4); 

dff_neg_async dff1 (count[0], cnt_b[0], clk, rst);
dff_neg_async dff2 (count[1], d2 , clk, rst);
dff_neg_async dff3 (count[2], d3 , clk, rst);
dff_neg_async dff4 (count[3], d4 , clk, rst);

endmodule

module dff_neg_async(q, d, clk, rst);

output reg q;
input d,clk,rst;

always @(negedge clk or posedge rst)
	begin
		if(rst) q <= 1'b0;
		else 	q <= d;
	end
endmodule

Lab3_Structural_Modelling/binary_counter.vcd
$date
	Tue Jan 30 15:41:21 2018
$end
$version
	Icarus Verilog
$end
$timescale
	1ps
$end
$scope module tb_binary_counter $end
$var wire 4 ! out [3:0] $end
$var reg 1 " clock $end
$var reg 1 # rst $end
$scope module uut $end
$var wire 1 " clk $end
$var wire 1 $ d2 $end
$var wire 1 % d3 $end
$var wire 1 & d4 $end
$var wire 1 # rst $end
$var wire 1 ' w1 $end
$var wire 1 ( w2 $end
$var wire 1 ) w3 $end
$var wire 1 * w4 $end
$var wire 1 + w5 $end
$var wire 4 , count [3:0] $end
$var wire 4 - cnt_b [3:0] $end
$scope module dff1 $end
$var wire 1 " clk $end
$var wire 1 . d $end
$var wire 1 # rst $end
$var reg 1 / q $end
$upscope $end
$scope module dff2 $end
$var wire 1 " clk $end
$var wire 1 $ d $end
$var wire 1 # rst $end
$var reg 1 0 q $end
$upscope $end
$scope module dff3 $end
$var wire 1 " clk $end
$var wire 1 % d $end
$var wire 1 # rst $end
$var reg 1 1 q $end
$upscope $end
$scope module dff4 $end
$var wire 1 " clk $end
$var wire 1 & d $end
$var wire 1 # rst $end
$var reg 1 2 q $end
$upscope $end
$upscope $end
$upscope $end
$enddefinitions $end
#0
$dumpvars
x2
x1
x0
x/
x.
bx -
bx ,
x+
x*
x)
x(
x'
x&
x%
x$
0#
0"
bx !
$end
#10000
1"
#20000
0%
0&
0$
1.
0)
0(
0*
0'
0+
b1111 -
02
01
00
b0 !
b0 ,
0/
0"
1#
#30000
1"
#40000
0"
#50000
1"
#60000
1$
0.
1+
b1110 -
b1 !
b1 ,
1/
0"
0#
#70000
1"
#80000
1.
b1101 -
0/
b10 !
b10 ,
10
0"
#90000
1"
#100000
1%
1(
0$
0.
1'
0+
b1100 -
b11 !
b11 ,
1/
0"
#110000
1"
#120000
1.
1%
0'
1(
b1011 -
0/
00
b100 !
b100 ,
11
0"
#130000
1"
#140000
1$
0.
1+
b1010 -
b101 !
b101 ,
1/
0"
#150000
1"
#160000
0$
1.
0%
0+
0(
b1111 -
0/
b0 !
b0 ,
01
0"
1#
#170000
1"
#180000
0"
#190000
1"
#200000
1$
0.
1+
b1110 -
b1 !
b1 ,
1/
0"
0#
#210000
1"
#220000
1.
b1101 -
10
b10 !
b10 ,
0/
0"
#230000
1"
#240000
1%
1(
0$
0.
1'
0+
b1100 -
b11 !
b11 ,
1/
0"
#250000
1"
#260000
1.
0'
b1011 -
11
00
b100 !
b100 ,
0/
0"
#270000
1"
#280000
1$
0.
1+
b1010 -
b101 !
b101 ,
1/
0"
#290000
1"
#300000
1.
b1001 -
10
b110 !
b110 ,
0/
0"
#310000
1"
#320000
0%
1&
0(
0$
0.
1*
1'
0+
b1000 -
b111 !
b111 ,
1/
0"
#330000
1"
#340000
1)
1&
1.
0*
0'
b111 -
12
01
00
b1000 !
b1000 ,
0/
0"
#350000
1"
#360000
0&
0)
0.
1+
b110 -
b1001 !
b1001 ,
1/
0"
#370000
1"
#380000
1.
0+
b1111 -
02
b0 !
b0 ,
0/
0"
#390000
1"
#400000
1$
0.
1+
b1110 -
b1 !
b1 ,
1/
0"
#410000
1"
#420000
1.
b1101 -
10
b10 !
b10 ,
0/
0"
#430000
1"
#440000
1%
1(
0$
0.
1'
0+
b1100 -
b11 !
b11 ,
1/
0"
#450000
1"
#460000
1.
0'
b1011 -
11
00
b100 !
b100 ,
0/
0"
#470000
1"
#480000
1$
0.
1+
b1010 -
b101 !
b101 ,
1/
0"
#490000
1"
#500000
1.
b1001 -
10
b110 !
b110 ,
0/
0"
#510000
1"
#520000
0%
1&
0(
0$
0.
1*
1'
0+
b1000 -
b111 !
b111 ,
1/
0"
#530000
1"
#540000
1)
1&
1.
0*
0'
b111 -
12
01
00
b1000 !
b1000 ,
0/
0"
#550000
1"
#560000
0&
0)
0.
1+
b110 -
b1001 !
b1001 ,
1/
0"
#570000
1"
#580000
1.
0+
b1111 -
02
b0 !
b0 ,
0/
0"
#590000
1"
#600000
1$
0.
1+
b1110 -
b1 !
b1 ,
1/
0"
#610000
1"
#620000
1.
b1101 -
10
b10 !
b10 ,
0/
0"
#630000
1"
#640000
1%
1(
0$
0.
1'
0+
b1100 -
b11 !
b11 ,
1/
0"
#650000
1"
#660000
1.
0'
b1011 -
11
00
b100 !
b100 ,
0/
0"
#670000
1"
#680000
1$
0.
1+
b1010 -
b101 !
b101 ,
1/
0"
#690000
1"
#700000
1.
b1001 -
10
b110 !
b110 ,
0/
0"
#710000
1"
#720000
0%
1&
0(
0$
0.
1*
1'
0+
b1000 -
b111 !
b111 ,
1/
0"
#730000
1"
#740000
1)
1&
1.
0*
0'
b111 -
12
01
00
b1000 !
b1000 ,
0/
0"
#750000
1"
#760000
0&
0)
0.
1+
b110 -
b1001 !
b1001 ,
1/
0"
#770000
1"
#780000
1.
0+
b1111 -
02
b0 !
b0 ,
0/
0"
#790000
1"
#800000
1$
0.
1+
b1110 -
b1 !
b1 ,
1/
0"
#810000
1"
#820000
1.
b1101 -
10
b10 !
b10 ,
0/
0"
#830000
1"
#840000
1%
1(
0$
0.
1'
0+
b1100 -
b11 !
b11 ,
1/
0"
#850000
1"
#860000
1.
0'
b1011 -
11
00
b100 !
b100 ,
0/
0"
#870000
1"
#880000
1$
0.
1+
b1010 -
b101 !
b101 ,
1/
0"
#890000
1"
#900000
1.
b1001 -
10
b110 !
b110 ,
0/
0"
#910000
1"
#920000
0%
1&
0(
0$
0.
1*
1'
0+
b1000 -
b111 !
b111 ,
1/
0"
#930000
1"
#940000
1)
1&
1.
0*
0'
b111 -
12
01
00
b1000 !
b1000 ,
0/
0"
#950000
1"
#960000
0&
0)
0.
1+
b110 -
b1001 !
b1001 ,
1/
0"
#970000
1"
#980000
1.
0+
b1111 -
02
b0 !
b0 ,
0/
0"
