Labtest_1/seqgen.v
// Kshitij Khandelwal
//2015A3PS0156P
module tb_seqgen();

	reg reset,clock;
	wire [3:0] out;

	seqgen uut(out,reset,clock);

	always #10 clock = ~clock;
		
	initial
		begin
		clock = 0; reset=0;
		#20 reset = 1;
		#40 reset = 0;
		#100 reset = 1;
		#40 reset = 0;
		#800 
		$stop;
		end
			
	initial
		begin
		$dumpfile("seqgen.vcd");
		$dumpvars;
		end
			
endmodule

module seqgen(out, reset, clk);
	input clk, reset;
	output reg [3:0] out;
	
	always @ (posedge clk)
		begin
				if(reset) out <= 4'b0000;
				else
					case(out)
						4'b0000: out <= 4'b0001;
						4'b0001: out <= 4'b0011;
						4'b0011: out <= 4'b0010;
						4'b0010: out <= 4'b0110;
						4'b0110: out <= 4'b0111;
						4'b0111: out <= 4'b0101;
						4'b0101: out <= 4'b0100;
						4'b0100: out <= 4'b1100;
						4'b1100: out <= 4'b1101;
						4'b1101: out <= 4'b1111;
						4'b1111: out <= 4'b1110;
						4'b1110: out <= 4'b1010;
						4'b1010: out <= 4'b1011;
						4'b1011: out <= 4'b1001;
						4'b1001: out <= 4'b1000;
						4'b1000: out <= 4'b0000;
						default: out <= 4'b0000;
					endcase
		end

endmodule

Labtest_1/seqgen.vcd
$date
	Tue Mar 13 15:19:07 2018
$end
$version
	Icarus Verilog
$end
$timescale
	1s
$end
$scope module tb_seqgen $end
$var wire 4 ! out [3:0] $end
$var reg 1 " clock $end
$var reg 1 # reset $end
$scope module uut $end
$var wire 1 " clk $end
$var wire 1 # reset $end
$var reg 4 $ out [3:0] $end
$upscope $end
$upscope $end
$enddefinitions $end
#0
$dumpvars
bx $
0#
0"
bx !
$end
#10
b0 !
b0 $
1"
#20
0"
1#
#30
1"
#40
0"
#50
1"
#60
0"
0#
#70
b1 !
b1 $
1"
#80
0"
#90
b11 !
b11 $
1"
#100
0"
#110
b10 !
b10 $
1"
#120
0"
#130
b110 !
b110 $
1"
#140
0"
#150
b111 !
b111 $
1"
#160
0"
1#
#170
b0 !
b0 $
1"
#180
0"
#190
1"
#200
0"
0#
#210
b1 !
b1 $
1"
#220
0"
#230
b11 !
b11 $
1"
#240
0"
#250
b10 !
b10 $
1"
#260
0"
#270
b110 !
b110 $
1"
#280
0"
#290
b111 !
b111 $
1"
#300
0"
#310
b101 !
b101 $
1"
#320
0"
#330
b100 !
b100 $
1"
#340
0"
#350
b1100 !
b1100 $
1"
#360
0"
#370
b1101 !
b1101 $
1"
#380
0"
#390
b1111 !
b1111 $
1"
#400
0"
#410
b1110 !
b1110 $
1"
#420
0"
#430
b1010 !
b1010 $
1"
#440
0"
#450
b1011 !
b1011 $
1"
#460
0"
#470
b1001 !
b1001 $
1"
#480
0"
#490
b1000 !
b1000 $
1"
#500
0"
#510
b0 !
b0 $
1"
#520
0"
#530
b1 !
b1 $
1"
#540
0"
#550
b11 !
b11 $
1"
#560
0"
#570
b10 !
b10 $
1"
#580
0"
#590
b110 !
b110 $
1"
#600
0"
#610
b111 !
b111 $
1"
#620
0"
#630
b101 !
b101 $
1"
#640
0"
#650
b100 !
b100 $
1"
#660
0"
#670
b1100 !
b1100 $
1"
#680
0"
#690
b1101 !
b1101 $
1"
#700
0"
#710
b1111 !
b1111 $
1"
#720
0"
#730
b1110 !
b1110 $
1"
#740
0"
#750
b1010 !
b1010 $
1"
#760
0"
#770
b1011 !
b1011 $
1"
#780
0"
#790
b1001 !
b1001 $
1"
#800
0"
#810
b1000 !
b1000 $
1"
#820
0"
#830
b0 !
b0 $
1"
#840
0"
#850
b1 !
b1 $
1"
#860
0"
#870
b11 !
b11 $
1"
#880
0"
#890
b10 !
b10 $
1"
#900
0"
#910
b110 !
b110 $
1"
#920
0"
#930
b111 !
b111 $
1"
#940
0"
#950
b101 !
b101 $
1"
#960
0"
#970
b100 !
b100 $
1"
#980
0"
#990
b1100 !
b1100 $
1"
