Lab2_Behavorial_Modelling/dff_neg_async.v
`timescale 1ns/10ps
//Negative edge triggered D flip flop with Active high asynchronous reset

module tb_dff_neg_async();

reg d,clk,rst;
wire q;

dff_neg_async uut(.q(q),.d(d),.clk(clk),.rst(rst));

// a clock with 100ns 50% duty cycle 	
initial
begin
#00 clk = 1'b0;
forever #50 clk = ~clk;
end
	
	
initial
begin
#00 rst=1'b0;
#70 rst=1'b1;
#100 rst=1'b0;
#500 rst=1'b1;
#100 rst=1'b0;
end
	
	
initial
begin
#000 d <= 1'b1;
#180 d <= 1'b0;
#100 d <= 1'b1;
#120 d <= 1'b0;
end

initial
begin
$dumpfile("dff_neg_async.vcd");
$dumpvars;
end
		
initial
begin
#1500 $stop;
end
endmodule


module dff_neg_async(q, d, clk, rst);

output reg q;
input d,clk,rst;

always @(negedge clk or posedge rst)
	begin
	if(rst)
	q <= 1'd0;
	else 
	q <= d;
	end
endmodule

Lab2_Behavorial_Modelling/dff_neg_async.vcd
$date
	Tue Jan 23 15:55:54 2018
$end
$version
	Icarus Verilog
$end
$timescale
	10ps
$end
$scope module tb_dff_neg_async $end
$var wire 1 ! q $end
$var reg 1 " clk $end
$var reg 1 # d $end
$var reg 1 $ rst $end
$scope module uut $end
$var wire 1 " clk $end
$var wire 1 # d $end
$var wire 1 $ rst $end
$var reg 1 ! q $end
$upscope $end
$upscope $end
$enddefinitions $end
#0
$dumpvars
0$
1#
0"
x!
$end
#5000
1"
#7000
0!
1$
#10000
0"
#15000
1"
#17000
0$
#18000
0#
#20000
0"
#25000
1"
#28000
1#
#30000
1!
0"
#35000
1"
#40000
0#
0"
#45000
1"
#50000
0!
0"
#55000
1"
#60000
0"
#65000
1"
#67000
1$
#70000
0"
#75000
1"
#77000
0$
