Lab2_Behavorial_Modelling/dff_pos_sync.v
//Positive edge triggered D flip flop with Active high synchronous reset
`timescale 1ns/10ps

module tb_dff_pos_sync();

	reg d,clk,rst;
	wire q;

	dff_pos_sync uut(.q(q),.d(d),.clk(clk),.rst(rst));
		
	initial
	begin
	#00 clk = 1'b0;
	forever #50 clk = ~clk;
	end
		
	initial
	begin
	#00 rst=1'b0;
	#70 rst=1'b1;
	#100 rst=1'b0;
	#500 rst=1'b1;
	#300 rst=1'b0;
	end
		
	initial
	begin
	#000 d <= 1'b1;
	#180 d <= 1'b0;
	#100 d <= 1'b1;
	#180 d <= 1'b0;
	#100 d <= 1'b1;
	end
			
	initial
	begin
		$dumpfile("dff_pos_sync.vcd");
		$dumpvars;
	end
			
	initial #1500 $stop;
			
endmodule


module dff_pos_sync(q, d, clk, rst);

	output reg q;
	input d,clk,rst;
		
	always @(posedge clk)
	begin
		if(rst)
		q <= 1'b0;
		else 
		q <= d;
	end

endmodule

Lab2_Behavorial_Modelling/dff_pos_sync.vcd
$date
	Tue Jan 23 15:28:45 2018
$end
$version
	Icarus Verilog
$end
$timescale
	10ps
$end
$scope module tb_dff_pos_sync $end
$var wire 1 ! q $end
$var reg 1 " clk $end
$var reg 1 # d $end
$var reg 1 $ rst $end
$scope module uut $end
$var wire 1 " clk $end
$var wire 1 # d $end
$var wire 1 $ rst $end
$var reg 1 ! q $end
$upscope $end
$upscope $end
$enddefinitions $end
#0
$dumpvars
0$
1#
0"
x!
$end
#5000
1!
1"
#7000
1$
#10000
0"
#15000
0!
1"
#17000
0$
#18000
0#
#20000
0"
#25000
1"
#28000
1#
#30000
0"
#35000
1!
1"
#40000
0"
#45000
1"
#46000
0#
#50000
0"
#55000
0!
1"
#56000
1#
#60000
0"
#65000
1!
1"
#67000
1$
#70000
0"
#75000
0!
1"
#80000
0"
#85000
1"
#90000
0"
#95000
1"
#97000
0$
#100000
0"
#105000
1!
1"
