Lab2_Behavorial_Modelling/mux.v
//4:1 Multiplexer

`timescale 1ns/10ps

module tb_mux(); 

reg [1:0] s;
reg [3:0] i;
wire o;

mux uut (o,i,s);

initial 
begin 
#0 i=4'b0101 ;
#20 s=2'b00 ; 
#20 s=2'b01 ;
#20 s=2'b10 ;
#20 s=2'b11 ;
#20 i=4'b1001 ; s=2'b00 ; 
#20 s=2'b01 ;
#20 s=2'b10 ;
#20 s=2'b11 ;
#20 $stop ; 
end

initial $monitor("t=%3d, input=%4b, select=%2b, out=%b",$time,i,s,o); 

initial
begin
$dumpfile("mux.vcd");
$dumpvars;
end

endmodule

module mux(out,in,select);

output out;
input [3:0] in;
input [1:0] select;

reg out;
always @( select or in )
begin
	case(select)
		2'b00: out<=in[0];
		2'b01: out<=in[1];
		2'b10: out<=in[2];
		2'b11: out<=in[3];
		default: out<=4'bzzzz;
	endcase
end
endmodule

Lab2_Behavorial_Modelling/mux.vcd
$date
	Tue Jan 23 15:58:23 2018
$end
$version
	Icarus Verilog
$end
$timescale
	10ps
$end
$scope module tb_mux $end
$var wire 1 ! o $end
$var reg 4 " i [3:0] $end
$var reg 2 # s [1:0] $end
$scope module uut $end
$var wire 4 $ in [3:0] $end
$var wire 2 % select [1:0] $end
$var reg 1 ! out $end
$upscope $end
$upscope $end
$enddefinitions $end
#0
$dumpvars
bx %
b101 $
bx #
b101 "
z!
$end
#2000
1!
b0 #
b0 %
#4000
0!
b1 #
b1 %
#6000
1!
b10 #
b10 %
#8000
0!
b11 #
b11 %
#10000
1!
b0 #
b0 %
b1001 "
b1001 $
#12000
0!
b1 #
b1 %
#14000
b10 #
b10 %
#16000
1!
b11 #
b11 %
