Homework_Assignment_2/bcd_updown.v
`timescale 1ns/10ps

module tb_bcd_updown();
	
	wire [7:0] count;
	reg clock, reset, control;

	bcd_updown uut (count, clock, reset, control);

	initial begin
		#00 clock = 1'b0;
		forever #10 clock = ~clock;
	end

	initial begin
		#00 reset = 1'b1; control = 1'b0;
		#10 reset = 1'b0;
		#10 reset = 1'b1;
		#1000 control = 1'b1;
		#1000 reset = 1'b0;
		#10 reset = 1'b1; 
		#1000 $finish;
	end

	initial begin
		$dumpfile("bcd_updown.vcd");
		$dumpvars;
	end

endmodule

module bcd_updown(count, clock, reset, control);

	output reg [7:0] count;
	input wire clock, reset, control;

	//Negative Edge Triggered Clock and Active Low Asynchronous Reset

	always @ (negedge clock or negedge reset)
	if (reset == 0)
			count <= 8'b0000_0000;
	else
		if (control == 1) //UP CONDITION	
			if (count == 8'b0101_1001)
				count <= 8'b0000_0000;
			else
				if (count[3:0] < 4'b1001)
					count <= count + 1;
				else begin
					count[7:4] <= count[7:4] + 1;
					count[3:0] <= 4'b0000;
				end
		else if (control == 0) //DOWN CONDITION
			if (count == 8'b0000_0000)
				count <= 8'b0101_1001; 
			else	
				if (count[3:0] > 4'b0000)
					count <= count - 1;
				else begin
					count[7:4] <= count[7:4] - 1;
					count[3:0] <= 4'b1001;
				end 
				
endmodule

Homework_Assignment_2/bcd_updown.vcd
$date
	Tue Apr 10 00:33:02 2018
$end
$version
	Icarus Verilog
$end
$timescale
	10ps
$end
$scope module tb_bcd_updown $end
$var wire 8 ! count [7:0] $end
$var reg 1 " clock $end
$var reg 1 # control $end
$var reg 1 $ reset $end
$scope module uut $end
$var wire 1 " clock $end
$var wire 1 # control $end
$var wire 1 $ reset $end
$var reg 8 % count [7:0] $end
$upscope $end
$upscope $end
$enddefinitions $end
#0
$dumpvars
bx1001 %
1$
0#
0"
bx1001 !
$end
#1000
b0 !
b0 %
0$
1"
#2000
b1011001 !
b1011001 %
1$
0"
#3000
1"
#4000
b1011000 !
b1011000 %
0"
#5000
1"
#6000
b1010111 !
b1010111 %
0"
#7000
1"
#8000
b1010110 !
b1010110 %
0"
#9000
1"
#10000
b1010101 !
b1010101 %
0"
#11000
1"
#12000
b1010100 !
b1010100 %
0"
#13000
1"
#14000
b1010011 !
b1010011 %
0"
#15000
1"
#16000
b1010010 !
b1010010 %
0"
#17000
1"
#18000
b1010001 !
b1010001 %
0"
#19000
1"
#20000
b1010000 !
b1010000 %
0"
#21000
1"
#22000
b1001001 !
b1001001 %
0"
#23000
1"
#24000
b1001000 !
b1001000 %
0"
#25000
1"
#26000
b1000111 !
b1000111 %
0"
#27000
1"
#28000
b1000110 !
b1000110 %
0"
#29000
1"
#30000
b1000101 !
b1000101 %
0"
#31000
1"
#32000
b1000100 !
b1000100 %
0"
#33000
1"
#34000
b1000011 !
b1000011 %
0"
#35000
1"
#36000
b1000010 !
b1000010 %
0"
#37000
1"
#38000
b1000001 !
b1000001 %
0"
#39000
1"
#40000
b1000000 !
b1000000 %
0"
#41000
1"
#42000
b111001 !
b111001 %
0"
#43000
1"
#44000
b111000 !
b111000 %
0"
#45000
1"
#46000
b110111 !
b110111 %
0"
#47000
1"
#48000
b110110 !
b110110 %
0"
#49000
1"
#50000
b110101 !
b110101 %
0"
#51000
1"
#52000
b110100 !
b110100 %
0"
#53000
1"
#54000
b110011 !
b110011 %
0"
#55000
1"
#56000
b110010 !
b110010 %
0"
#57000
1"
#58000
b110001 !
b110001 %
0"
#59000
1"
#60000
b110000 !
b110000 %
0"
#61000
1"
#62000
b101001 !
b101001 %
0"
#63000
1"
#64000
b101000 !
b101000 %
0"
#65000
1"
#66000
b100111 !
b100111 %
0"
#67000
1"
#68000
b100110 !
b100110 %
0"
#69000
1"
#70000
b100101 !
b100101 %
0"
#71000
1"
#72000
b100100 !
b100100 %
0"
#73000
1"
#74000
b100011 !
b100011 %
0"
#75000
1"
#76000
b100010 !
b100010 %
0"
#77000
1"
#78000
b100001 !
b100001 %
0"
#79000
1"
#80000
b100000 !
b100000 %
0"
#81000
1"
#82000
b11001 !
b11001 %
0"
#83000
1"
#84000
b11000 !
b11000 %
0"
#85000
1"
#86000
b10111 !
b10111 %
0"
#87000
1"
#88000
b10110 !
b10110 %
0"
#89000
1"
#90000
b10101 !
b10101 %
0"
#91000
1"
#92000
b10100 !
b10100 %
0"
#93000
1"
#94000
b10011 !
b10011 %
0"
#95000
1"
#96000
b10010 !
b10010 %
0"
#97000
1"
#98000
b10001 !
b10001 %
0"
#99000
1"
#100000
b10000 !
b10000 %
0"
#101000
1"
#102000
b10001 !
b10001 %
0"
1#
#103000
1"
#104000
b10010 !
b10010 %
0"
#105000
1"
#106000
b10011 !
b10011 %
0"
#107000
1"
#108000
b10100 !
b10100 %
0"
#109000
1"
#110000
b10101 !
b10101 %
0"
#111000
1"
#112000
b10110 !
b10110 %
0"
#113000
1"
#114000
b10111 !
b10111 %
0"
#115000
1"
#116000
b11000 !
b11000 %
0"
#117000
1"
#118000
b11001 !
b11001 %
0"
#119000
1"
#120000
b100000 !
b100000 %
0"
#121000
1"
#122000
b100001 !
b100001 %
0"
#123000
1"
#124000
b100010 !
b100010 %
0"
#125000
1"
#126000
b100011 !
b100011 %
0"
#127000
1"
#128000
b100100 !
b100100 %
0"
#129000
1"
#130000
b100101 !
b100101 %
0"
#131000
1"
#132000
b100110 !
b100110 %
0"
#133000
1"
#134000
b100111 !
b100111 %
0"
#135000
1"
#136000
b101000 !
b101000 %
0"
#137000
1"
#138000
b101001 !
b101001 %
0"
#139000
1"
#140000
b110000 !
b110000 %
0"
#141000
1"
#142000
b110001 !
b110001 %
0"
#143000
1"
#144000
b110010 !
b110010 %
0"
#145000
1"
#146000
b110011 !
b110011 %
0"
#147000
1"
#148000
b110100 !
b110100 %
0"
#149000
1"
#150000
b110101 !
b110101 %
0"
#151000
1"
#152000
b110110 !
b110110 %
0"
#153000
1"
#154000
b110111 !
b110111 %
0"
#155000
1"
#156000
b111000 !
b111000 %
0"
#157000
1"
#158000
b111001 !
b111001 %
0"
#159000
1"
#160000
b1000000 !
b1000000 %
0"
#161000
1"
#162000
b1000001 !
b1000001 %
0"
#163000
1"
#164000
b1000010 !
b1000010 %
0"
#165000
1"
#166000
b1000011 !
b1000011 %
0"
#167000
1"
#168000
b1000100 !
b1000100 %
0"
#169000
1"
#170000
b1000101 !
b1000101 %
0"
#171000
1"
#172000
b1000110 !
b1000110 %
0"
#173000
1"
#174000
b1000111 !
b1000111 %
0"
#175000
1"
#176000
b1001000 !
b1001000 %
0"
#177000
1"
#178000
b1001001 !
b1001001 %
0"
#179000
1"
#180000
b1010000 !
b1010000 %
0"
#181000
1"
#182000
b1010001 !
b1010001 %
0"
#183000
1"
#184000
b1010010 !
b1010010 %
0"
#185000
1"
#186000
b1010011 !
b1010011 %
0"
#187000
1"
#188000
b1010100 !
b1010100 %
0"
#189000
1"
#190000
b1010101 !
b1010101 %
0"
#191000
1"
#192000
b1010110 !
b1010110 %
0"
#193000
1"
#194000
b1010111 !
b1010111 %
0"
#195000
1"
#196000
b1011000 !
b1011000 %
0"
#197000
1"
#198000
b1011001 !
b1011001 %
0"
#199000
1"
#200000
b0 !
b0 %
0"
#201000
1"
#202000
0"
0$
#203000
1"
1$
#204000
b1 !
b1 %
0"
#205000
1"
#206000
b10 !
b10 %
0"
#207000
1"
#208000
b11 !
b11 %
0"
#209000
1"
#210000
b100 !
b100 %
0"
#211000
1"
#212000
b101 !
b101 %
0"
#213000
1"
#214000
b110 !
b110 %
0"
#215000
1"
#216000
b111 !
b111 %
0"
#217000
1"
#218000
b1000 !
b1000 %
0"
#219000
1"
#220000
b1001 !
b1001 %
0"
#221000
1"
#222000
b10000 !
b10000 %
0"
#223000
1"
#224000
b10001 !
b10001 %
0"
#225000
1"
#226000
b10010 !
b10010 %
0"
#227000
1"
#228000
b10011 !
b10011 %
0"
#229000
1"
#230000
b10100 !
b10100 %
0"
#231000
1"
#232000
b10101 !
b10101 %
0"
#233000
1"
#234000
b10110 !
b10110 %
0"
#235000
1"
#236000
b10111 !
b10111 %
0"
#237000
1"
#238000
b11000 !
b11000 %
0"
#239000
1"
#240000
b11001 !
b11001 %
0"
#241000
1"
#242000
b100000 !
b100000 %
0"
#243000
1"
#244000
b100001 !
b100001 %
0"
#245000
1"
#246000
b100010 !
b100010 %
0"
#247000
1"
#248000
b100011 !
b100011 %
0"
#249000
1"
#250000
b100100 !
b100100 %
0"
#251000
1"
#252000
b100101 !
b100101 %
0"
#253000
1"
#254000
b100110 !
b100110 %
0"
#255000
1"
#256000
b100111 !
b100111 %
0"
#257000
1"
#258000
b101000 !
b101000 %
0"
#259000
1"
#260000
b101001 !
b101001 %
0"
#261000
1"
#262000
b110000 !
b110000 %
0"
#263000
1"
#264000
b110001 !
b110001 %
0"
#265000
1"
#266000
b110010 !
b110010 %
0"
#267000
1"
#268000
b110011 !
b110011 %
0"
#269000
1"
#270000
b110100 !
b110100 %
0"
#271000
1"
#272000
b110101 !
b110101 %
0"
#273000
1"
#274000
b110110 !
b110110 %
0"
#275000
1"
#276000
b110111 !
b110111 %
0"
#277000
1"
#278000
b111000 !
b111000 %
0"
#279000
1"
#280000
b111001 !
b111001 %
0"
#281000
1"
#282000
b1000000 !
b1000000 %
0"
#283000
1"
#284000
b1000001 !
b1000001 %
0"
#285000
1"
#286000
b1000010 !
b1000010 %
0"
#287000
1"
#288000
b1000011 !
b1000011 %
0"
#289000
1"
#290000
b1000100 !
b1000100 %
0"
#291000
1"
#292000
b1000101 !
b1000101 %
0"
#293000
1"
#294000
b1000110 !
b1000110 %
0"
#295000
1"
#296000
b1000111 !
b1000111 %
0"
#297000
1"
#298000
b1001000 !
b1001000 %
0"
#299000
1"
#300000
b1001001 !
b1001001 %
0"
#301000
1"
#302000
b1010000 !
b1010000 %
0"
