Homework_Assignment_2/divider_8bit.v
`timescale 1ns/10ps

module tb_divider_8bit();

	wire [7:0] quotient, remainder;
	wire eop;
	reg [7:0] divisor, dividend;
	reg clk, rst;

	divider_8bit uut (quotient, remainder, eop, divisor, dividend, clk, rst);

	initial begin
		#0 clk = 1'b0;
		forever #10 clk = ~clk;
	end

	initial begin
		$dumpfile("divider_8bit.vcd");
		$dumpvars;
	end

	initial begin 
		#00 clk = 1'b0; rst = 1'b0;
		#05 rst = 1'b1;
		#05 dividend = 8'b0100_1000; divisor = 8'b0000_1011; rst = 1'b0;
		#200 $finish;
	end

endmodule

module divider_8bit (quotient, remainder, eop, divisor, dividend, clk, rst);

	output reg [7:0] quotient, remainder;
	output reg eop;
	input wire [7:0] divisor, dividend;
	input wire clk, rst;
	
	reg [7:0] divd;
	//Negative Edge Triggered Clock and Active High Asynchronous Reset
	//Currently only for unsigned numbers
	always @ (dividend)
		divd = dividend;

	always @ (negedge clk or posedge rst)
	begin
		if(rst)
		begin
			quotient = 8'b0000_0000;
			remainder = 8'b0000_0000;
			eop = 1'b0;
			divd = dividend;
		end
		else if ((dividend[7] == 0) && (divisor[7]==0))
			if (divd >= divisor)
			begin
				eop = 0;
				divd = divd - divisor;
				quotient = quotient + 1;
				remainder = divd;
			end
			else eop = 1;
	end

	always @ (eop or negedge clk)
		if (eop)
			eop = 1'b0;
endmodule

Homework_Assignment_2/divider_8bit.vcd
$date
	Tue Apr 10 04:39:02 2018
$end
$version
	Icarus Verilog
$end
$timescale
	10ps
$end
$scope module tb_divider_8bit $end
$var wire 8 ! remainder [7:0] $end
$var wire 8 " quotient [7:0] $end
$var wire 1 # eop $end
$var reg 1 $ clk $end
$var reg 8 % dividend [7:0] $end
$var reg 8 & divisor [7:0] $end
$var reg 1 ' rst $end
$scope module uut $end
$var wire 1 $ clk $end
$var wire 8 ( dividend [7:0] $end
$var wire 8 ) divisor [7:0] $end
$var wire 1 ' rst $end
$var reg 8 * divd [7:0] $end
$var reg 1 # eop $end
$var reg 8 + quotient [7:0] $end
$var reg 8 , remainder [7:0] $end
$upscope $end
$upscope $end
$enddefinitions $end
#0
$dumpvars
bx ,
bx +
bx *
bx )
bx (
0'
bx &
bx %
0$
x#
bx "
bx !
$end
#500
0#
b0 !
b0 ,
b0 "
b0 +
1'
#1000
b1001000 *
0'
b1011 &
b1011 )
b1001000 %
b1001000 (
1$
#2000
b111101 !
b111101 ,
b1 "
b1 +
b111101 *
0$
#3000
1$
#4000
b110010 !
b110010 ,
b10 "
b10 +
b110010 *
0$
#5000
1$
#6000
b100111 !
b100111 ,
b11 "
b11 +
b100111 *
0$
#7000
1$
#8000
b11100 !
b11100 ,
b100 "
b100 +
b11100 *
0$
#9000
1$
#10000
b10001 !
b10001 ,
b101 "
b101 +
b10001 *
0$
#11000
1$
#12000
b110 !
b110 ,
b110 "
b110 +
b110 *
0$
#13000
1$
#14000
0#
0$
#15000
1$
#16000
0#
0$
#17000
1$
#18000
0#
0$
#19000
1$
#20000
0#
0$
