Lab5_RAM_Memory/ram_64B.v
`timescale 1ns/10ps

module tb_ram_64B();

reg clk,rwb;
reg [5:0]adrb;
wire [7:0]dout;
wire [7:0]din;
reg [7:0] memory[0:63];

ram_64B uut (dout,din,clk,rwb,adrb);
two_comp utt (din,dout);

initial
begin
#00 clk <= 1'b0;
forever #50 clk <= ~ clk ;
end

initial
begin
#00 rwb <= 1'b1;
forever #100 rwb <= ~ rwb ;
end

initial
begin 
  adrb = 0;
  repeat( 64 ) 
  begin 
     #200 adrb = adrb + 8'd1; 
  end 
end 

initial
begin
$dumpfile("ram_64B.vcd");
$dumpvars;
end

initial #12800 $finish;

endmodule



module ram_64B(dout,din,clk,rwb,adrb);

input clk,rwb;
input [5:0]adrb;
output reg [7:0]dout;
input [7:0]din;
reg [7:0] memory[0:63];

initial $readmemh("data_64.txt",memory);

always@(posedge clk)
	begin
		if(rwb) dout <= memory[adrb];
		else memory[adrb] <= din;
	end
endmodule


module two_comp(comp, in);
output [7:0]comp;
input [7:0]in;
assign comp = ~in + 8'd1;
endmodule

Lab5_RAM_Memory/ram_64B.vcd
$date
	Tue Feb 20 14:55:26 2018
$end
$version
	Icarus Verilog
$end
$timescale
	10ps
$end
$scope module tb_ram_64B $end
$var wire 8 ! dout [7:0] $end
$var wire 8 " din [7:0] $end
$var reg 6 # adrb [5:0] $end
$var reg 1 $ clk $end
$var reg 1 % rwb $end
$scope module utt $end
$var wire 8 & in [7:0] $end
$var wire 8 ' comp [7:0] $end
$upscope $end
$scope module uut $end
$var wire 6 ( adrb [5:0] $end
$var wire 1 $ clk $end
$var wire 8 ) din [7:0] $end
$var wire 1 % rwb $end
$var reg 8 * dout [7:0] $end
$upscope $end
$upscope $end
$enddefinitions $end
#0
$dumpvars
bx *
bx )
b0 (
bx '
bx &
1%
0$
b0 #
bx "
bx !
$end
#5000
b0 "
b0 '
b0 )
b0 !
b0 &
b0 *
1$
#10000
0$
0%
#15000
1$
#20000
0$
1%
b1 #
b1 (
#25000
b11101111 "
b11101111 '
b11101111 )
b10001 !
b10001 &
b10001 *
1$
#30000
0$
0%
#35000
1$
#40000
0$
1%
b10 #
b10 (
#45000
b11011110 "
b11011110 '
b11011110 )
b100010 !
b100010 &
b100010 *
1$
#50000
0$
0%
#55000
1$
#60000
0$
1%
b11 #
b11 (
#65000
b11001101 "
b11001101 '
b11001101 )
b110011 !
b110011 &
b110011 *
1$
#70000
0$
0%
#75000
1$
#80000
0$
1%
b100 #
b100 (
#85000
b10111100 "
b10111100 '
b10111100 )
b1000100 !
b1000100 &
b1000100 *
1$
#90000
0$
0%
#95000
1$
#100000
0$
1%
b101 #
b101 (
#105000
b10101011 "
b10101011 '
b10101011 )
b1010101 !
b1010101 &
b1010101 *
1$
#110000
0$
0%
#115000
1$
#120000
0$
1%
b110 #
b110 (
#125000
b10011010 "
b10011010 '
b10011010 )
b1100110 !
b1100110 &
b1100110 *
1$
#130000
0$
0%
#135000
1$
#140000
0$
1%
b111 #
b111 (
#145000
b10001001 "
b10001001 '
b10001001 )
b1110111 !
b1110111 &
b1110111 *
1$
#150000
0$
0%
#155000
1$
#160000
0$
1%
b1000 #
b1000 (
#165000
b1111000 "
b1111000 '
b1111000 )
b10001000 !
b10001000 &
b10001000 *
1$
#170000
0$
0%
#175000
1$
#180000
0$
1%
b1001 #
b1001 (
#185000
b1100111 "
b1100111 '
b1100111 )
b10011001 !
b10011001 &
b10011001 *
1$
#190000
0$
0%
#195000
1$
#200000
0$
1%
b1010 #
b1010 (
#205000
b1010110 "
b1010110 '
b1010110 )
b10101010 !
b10101010 &
b10101010 *
1$
#210000
0$
0%
#215000
1$
#220000
0$
1%
b1011 #
b1011 (
#225000
b1000101 "
b1000101 '
b1000101 )
b10111011 !
b10111011 &
b10111011 *
1$
#230000
0$
0%
#235000
1$
#240000
0$
1%
b1100 #
b1100 (
#245000
b110100 "
b110100 '
b110100 )
b11001100 !
b11001100 &
b11001100 *
1$
#250000
0$
0%
#255000
1$
#260000
0$
1%
b1101 #
b1101 (
#265000
b100011 "
b100011 '
b100011 )
b11011101 !
b11011101 &
b11011101 *
1$
#270000
0$
0%
#275000
1$
#280000
0$
1%
b1110 #
b1110 (
#285000
b10010 "
b10010 '
b10010 )
b11101110 !
b11101110 &
b11101110 *
1$
#290000
0$
0%
#295000
1$
#300000
0$
1%
b1111 #
b1111 (
#305000
b1 "
b1 '
b1 )
b11111111 !
b11111111 &
b11111111 *
1$
#310000
0$
0%
#315000
1$
#320000
0$
1%
b10000 #
b10000 (
#325000
b0 "
b0 '
b0 )
b0 !
b0 &
b0 *
1$
#330000
0$
0%
#335000
1$
#340000
0$
1%
b10001 #
b10001 (
#345000
b11101111 "
b11101111 '
b11101111 )
b10001 !
b10001 &
b10001 *
1$
#350000
0$
0%
#355000
1$
#360000
0$
1%
b10010 #
b10010 (
#365000
b11011110 "
b11011110 '
b11011110 )
b100010 !
b100010 &
b100010 *
1$
#370000
0$
0%
#375000
1$
#380000
0$
1%
b10011 #
b10011 (
#385000
b11001101 "
b11001101 '
b11001101 )
b110011 !
b110011 &
b110011 *
1$
#390000
0$
0%
#395000
1$
#400000
0$
1%
b10100 #
b10100 (
#405000
b10111100 "
b10111100 '
b10111100 )
b1000100 !
b1000100 &
b1000100 *
1$
#410000
0$
0%
#415000
1$
#420000
0$
1%
b10101 #
b10101 (
#425000
b10101011 "
b10101011 '
b10101011 )
b1010101 !
b1010101 &
b1010101 *
1$
#430000
0$
0%
#435000
1$
#440000
0$
1%
b10110 #
b10110 (
#445000
b10011010 "
b10011010 '
b10011010 )
b1100110 !
b1100110 &
b1100110 *
1$
#450000
0$
0%
#455000
1$
#460000
0$
1%
b10111 #
b10111 (
#465000
b10001001 "
b10001001 '
b10001001 )
b1110111 !
b1110111 &
b1110111 *
1$
#470000
0$
0%
#475000
1$
#480000
0$
1%
b11000 #
b11000 (
#485000
b1111000 "
b1111000 '
b1111000 )
b10001000 !
b10001000 &
b10001000 *
1$
#490000
0$
0%
#495000
1$
#500000
0$
1%
b11001 #
b11001 (
#505000
b1100111 "
b1100111 '
b1100111 )
b10011001 !
b10011001 &
b10011001 *
1$
#510000
0$
0%
#515000
1$
#520000
0$
1%
b11010 #
b11010 (
#525000
b1010110 "
b1010110 '
b1010110 )
b10101010 !
b10101010 &
b10101010 *
1$
#530000
0$
0%
#535000
1$
#540000
0$
1%
b11011 #
b11011 (
#545000
b1000101 "
b1000101 '
b1000101 )
b10111011 !
b10111011 &
b10111011 *
1$
#550000
0$
0%
#555000
1$
#560000
0$
1%
b11100 #
b11100 (
#565000
b110100 "
b110100 '
b110100 )
b11001100 !
b11001100 &
b11001100 *
1$
#570000
0$
0%
#575000
1$
#580000
0$
1%
b11101 #
b11101 (
#585000
b100011 "
b100011 '
b100011 )
b11011101 !
b11011101 &
b11011101 *
1$
#590000
0$
0%
#595000
1$
#600000
0$
1%
b11110 #
b11110 (
#605000
b10010 "
b10010 '
b10010 )
b11101110 !
b11101110 &
b11101110 *
1$
#610000
0$
0%
#615000
1$
#620000
0$
1%
b11111 #
b11111 (
#625000
b1 "
b1 '
b1 )
b11111111 !
b11111111 &
b11111111 *
1$
#630000
0$
0%
#635000
1$
#640000
0$
1%
b100000 #
b100000 (
#645000
b0 "
b0 '
b0 )
b0 !
b0 &
b0 *
1$
#650000
0$
0%
#655000
1$
#660000
0$
1%
b100001 #
b100001 (
#665000
b11101111 "
b11101111 '
b11101111 )
b10001 !
b10001 &
b10001 *
1$
#670000
0$
0%
#675000
1$
#680000
0$
1%
b100010 #
b100010 (
#685000
b11011110 "
b11011110 '
b11011110 )
b100010 !
b100010 &
b100010 *
1$
#690000
0$
0%
#695000
1$
#700000
0$
1%
b100011 #
b100011 (
#705000
b11001101 "
b11001101 '
b11001101 )
b110011 !
b110011 &
b110011 *
1$
#710000
0$
0%
#715000
1$
#720000
0$
1%
b100100 #
b100100 (
#725000
b10111100 "
b10111100 '
b10111100 )
b1000100 !
b1000100 &
b1000100 *
1$
#730000
0$
0%
#735000
1$
#740000
0$
1%
b100101 #
b100101 (
#745000
b10101011 "
b10101011 '
b10101011 )
b1010101 !
b1010101 &
b1010101 *
1$
#750000
0$
0%
#755000
1$
#760000
0$
1%
b100110 #
b100110 (
#765000
b10011010 "
b10011010 '
b10011010 )
b1100110 !
b1100110 &
b1100110 *
1$
#770000
0$
0%
#775000
1$
#780000
0$
1%
b100111 #
b100111 (
#785000
b10001001 "
b10001001 '
b10001001 )
b1110111 !
b1110111 &
b1110111 *
1$
#790000
0$
0%
#795000
1$
#800000
0$
1%
b101000 #
b101000 (
#805000
b1111000 "
b1111000 '
b1111000 )
b10001000 !
b10001000 &
b10001000 *
1$
#810000
0$
0%
#815000
1$
#820000
0$
1%
b101001 #
b101001 (
#825000
b1100111 "
b1100111 '
b1100111 )
b10011001 !
b10011001 &
b10011001 *
1$
#830000
0$
0%
#835000
1$
#840000
0$
1%
b101010 #
b101010 (
#845000
b1010110 "
b1010110 '
b1010110 )
b10101010 !
b10101010 &
b10101010 *
1$
#850000
0$
0%
#855000
1$
#860000
0$
1%
b101011 #
b101011 (
#865000
b1000101 "
b1000101 '
b1000101 )
b10111011 !
b10111011 &
b10111011 *
1$
#870000
0$
0%
#875000
1$
#880000
0$
1%
b101100 #
b101100 (
#885000
b110100 "
b110100 '
b110100 )
b11001100 !
b11001100 &
b11001100 *
1$
#890000
0$
0%
#895000
1$
#900000
0$
1%
b101101 #
b101101 (
#905000
b100011 "
b100011 '
b100011 )
b11011101 !
b11011101 &
b11011101 *
1$
#910000
0$
0%
#915000
1$
#920000
0$
1%
b101110 #
b101110 (
#925000
b10010 "
b10010 '
b10010 )
b11101110 !
b11101110 &
b11101110 *
1$
#930000
0$
0%
#935000
1$
#940000
0$
1%
b101111 #
b101111 (
#945000
b1 "
b1 '
b1 )
b11111111 !
b11111111 &
b11111111 *
1$
#950000
0$
0%
#955000
1$
#960000
0$
1%
b110000 #
b110000 (
#965000
b0 "
b0 '
b0 )
b0 !
b0 &
b0 *
1$
#970000
0$
0%
#975000
1$
#980000
0$
1%
b110001 #
b110001 (
#985000
b11101111 "
b11101111 '
b11101111 )
b10001 !
b10001 &
b10001 *
1$
#990000
0$
0%
#995000
1$
#1000000
0$
1%
b110010 #
b110010 (
#1005000
b11011110 "
b11011110 '
b11011110 )
b100010 !
b100010 &
b100010 *
1$
#1010000
0$
0%
#1015000
1$
#1020000
0$
1%
b110011 #
b110011 (
#1025000
b11001101 "
b11001101 '
b11001101 )
b110011 !
b110011 &
b110011 *
1$
#1030000
0$
0%
#1035000
1$
#1040000
0$
1%
b110100 #
b110100 (
#1045000
b10111100 "
b10111100 '
b10111100 )
b1000100 !
b1000100 &
b1000100 *
1$
#1050000
0$
0%
#1055000
1$
#1060000
0$
1%
b110101 #
b110101 (
#1065000
b10101011 "
b10101011 '
b10101011 )
b1010101 !
b1010101 &
b1010101 *
1$
#1070000
0$
0%
#1075000
1$
#1080000
0$
1%
b110110 #
b110110 (
#1085000
b10011010 "
b10011010 '
b10011010 )
b1100110 !
b1100110 &
b1100110 *
1$
#1090000
0$
0%
#1095000
1$
#1100000
0$
1%
b110111 #
b110111 (
#1105000
b10001001 "
b10001001 '
b10001001 )
b1110111 !
b1110111 &
b1110111 *
1$
#1110000
0$
0%
#1115000
1$
#1120000
0$
1%
b111000 #
b111000 (
#1125000
b1111000 "
b1111000 '
b1111000 )
b10001000 !
b10001000 &
b10001000 *
1$
#1130000
0$
0%
#1135000
1$
#1140000
0$
1%
b111001 #
b111001 (
#1145000
b1100111 "
b1100111 '
b1100111 )
b10011001 !
b10011001 &
b10011001 *
1$
#1150000
0$
0%
#1155000
1$
#1160000
0$
1%
b111010 #
b111010 (
#1165000
b1010110 "
b1010110 '
b1010110 )
b10101010 !
b10101010 &
b10101010 *
1$
#1170000
0$
0%
#1175000
1$
#1180000
0$
1%
b111011 #
b111011 (
#1185000
b1000101 "
b1000101 '
b1000101 )
b10111011 !
b10111011 &
b10111011 *
1$
#1190000
0$
0%
#1195000
1$
#1200000
0$
1%
b111100 #
b111100 (
#1205000
b110100 "
b110100 '
b110100 )
b11001100 !
b11001100 &
b11001100 *
1$
#1210000
0$
0%
#1215000
1$
#1220000
0$
1%
b111101 #
b111101 (
#1225000
b100011 "
b100011 '
b100011 )
b11011101 !
b11011101 &
b11011101 *
1$
#1230000
0$
0%
#1235000
1$
#1240000
0$
1%
b111110 #
b111110 (
#1245000
b10010 "
b10010 '
b10010 )
b11101110 !
b11101110 &
b11101110 *
1$
#1250000
0$
0%
#1255000
1$
#1260000
0$
1%
b111111 #
b111111 (
#1265000
b1 "
b1 '
b1 )
b11111111 !
b11111111 &
b11111111 *
1$
#1270000
0$
0%
#1275000
1$
#1280000
0$
1%
b0 #
b0 (
