Homework_Assignment_1/comparator_8bit.v
`timescale 1ns/10ps

module tb_comparator_8bit(); 

	reg [7:0] A,B ;
	reg sign; 
	wire AeqB, AgtB, AltB ; 

	comparator_8bit uut (.AeqB(AeqB),.AgtB(AgtB),.AltB(AltB),.A(A),.B(B),.sign(sign));

	initial 
	begin 
		#00 A = 8'b00000000 ; B = 8'b0000_0000 ; sign = 0;
		#20 A = 8'b00001111 ; B = 8'b0000_1111 ; sign = 0;
		#20 A = 8'b11110000 ; B = 8'b0000_1111 ; sign = 0;
		#20 A = 8'b00111100 ; B = 8'b1110_0000 ; sign = 0;
		#20 A = 8'b11000011 ; B = 8'b1110_0000 ; sign = 1;
		#20 A = 8'b00100000 ; B = 8'b0000_0000 ; sign = 0;
		#20 A = 8'b00100000 ; B = 8'b0000_0000 ; sign = 0;
		#20 A = 8'b11100000 ; B = 8'b0000_0000 ; sign = 1;
		#20 A = 8'b11100111 ; B = 8'b0000_0000 ; sign = 1;
		#20 A = 8'b00000000 ; B = 8'b0000_0000 ; sign = 0;
		#20 A = 8'b00000000 ; B = 8'b0000_0000 ; sign = 1;
		#20 A = 8'b00001111 ; B = 8'b1000_0000 ; sign = 0;
		#20 A = 8'b00001111 ; B = 8'b1000_0000 ; sign = 1;
		#20 $stop ; 
	end

	initial $monitor("t=%3d, A=%b,B=%b,sign=%b,AeqB=%b,AgtB=%b AltB=%b",$time,A,B,sign,AeqB, AgtB, AltB); 

	initial
	begin
		$dumpfile("comparator_8bit.vcd");
		$dumpvars;
	end
		
endmodule

module comparator_8bit(AeqB, AgtB, AltB, A, B, sign);

	output AeqB, AgtB, AltB ;
	input [7:0] A, B ;
	input sign ;

	assign AeqB = (A==B)? 1 : 0 ; 
	assign AgtB = sign?(A[7]?(B[7]?(A<B):0):(B[7]?1:(A>B))):(A>B);
	assign AltB = sign?(A[7]?(B[7]?(A>B):1):(B[7]?0:(A<B))):(A<B);
endmodule

Homework_Assignment_1/comparator_8bit.vcd
$date
	Mon Mar 12 00:51:49 2018
$end
$version
	Icarus Verilog
$end
$timescale
	10ps
$end
$scope module tb_comparator_8bit $end
$var wire 1 ! AltB $end
$var wire 1 " AgtB $end
$var wire 1 # AeqB $end
$var reg 8 $ A [7:0] $end
$var reg 8 % B [7:0] $end
$var reg 1 & sign $end
$scope module uut $end
$var wire 8 ' A [7:0] $end
$var wire 8 ( B [7:0] $end
$var wire 1 & sign $end
$var wire 1 ! AltB $end
$var wire 1 " AgtB $end
$var wire 1 # AeqB $end
$upscope $end
$upscope $end
$enddefinitions $end
#0
$dumpvars
b0 (
b0 '
0&
b0 %
b0 $
1#
0"
0!
$end
#2000
b1111 %
b1111 (
b1111 $
b1111 '
#4000
0#
1"
b11110000 $
b11110000 '
#6000
0"
1!
b11100000 %
b11100000 (
b111100 $
b111100 '
#8000
1"
0!
1&
b11000011 $
b11000011 '
#10000
0&
b0 %
b0 (
b100000 $
b100000 '
#14000
0"
1!
1&
b11100000 $
b11100000 '
#16000
b11100111 $
b11100111 '
#18000
0!
1#
0&
b0 $
b0 '
#20000
1&
#22000
1!
0#
0&
b10000000 %
b10000000 (
b1111 $
b1111 '
#24000
1"
0!
1&
